pointtorch/__init__.py
pointtorch/py.typed
pointtorch/config/__init__.py
pointtorch/config/_optional_dependencies.py
pointtorch/core/__init__.py
pointtorch/core/_bounding_box.py
pointtorch/core/_point_cloud.py
pointtorch/core/_read.py
pointtorch/io/__init__.py
pointtorch/io/_base_point_cloud_reader.py
pointtorch/io/_base_point_cloud_writer.py
pointtorch/io/_csv_reader.py
pointtorch/io/_csv_writer.py
pointtorch/io/_download_file.py
pointtorch/io/_hdf_reader.py
pointtorch/io/_hdf_writer.py
pointtorch/io/_las_reader.py
pointtorch/io/_las_writer.py
pointtorch/io/_point_cloud_io_data.py
pointtorch/io/_point_cloud_reader.py
pointtorch/io/_point_cloud_writer.py
pointtorch/io/_unzip.py
pointtorch/operations/__init__.py
pointtorch/operations/numpy/__init__.py
pointtorch/operations/numpy/_fit_oriented_bounding_box.py
pointtorch/operations/numpy/_make_labels_consecutive.py
pointtorch/operations/numpy/_non_max_suppression.py
pointtorch/operations/numpy/_voxel_downsampling.py
pointtorch/operations/torch/__init__.py
pointtorch/operations/torch/_knn_search.py
pointtorch/operations/torch/_make_labels_consecutive.py
pointtorch/operations/torch/_max_pooling.py
pointtorch/operations/torch/_neighbor_search.py
pointtorch/operations/torch/_pack_batch.py
pointtorch/operations/torch/_radius_search.py
pointtorch/operations/torch/_random_sampling.py
pointtorch/operations/torch/_ravel_index.py
pointtorch/operations/torch/_shuffle.py
pointtorch/operations/torch/_voxel_downsampling.py
pointtorch-0.2.0.dist-info/LICENSE
pointtorch-0.2.0.dist-info/METADATA
pointtorch-0.2.0.dist-info/WHEEL
pointtorch-0.2.0.dist-info/top_level.txt
pointtorch-0.2.0.dist-info/RECORD
