Metadata-Version: 2.2
Name: pointtorch
Version: 0.2.0
Summary: A Python Package for Deep Learning on 3D Point Clouds Using PyTorch.
Author-email: Josafat-Mattias Burmeister <burmeister@uni-potsdam.de>
Maintainer-email: Josafat-Mattias Burmeister <burmeister@uni-potsdam.de>
License: MIT License
Project-URL: Homepage, https://github.com/ai4trees/pointtorch
Project-URL: Documentation, https://ai4trees.github.io/pointtorch/
Project-URL: Repository, https://github.com/ai4trees/pointtorch.git
Project-URL: Issues, https://github.com/ai4trees/pointtorch/issues
Project-URL: Changelog, https://ai4trees.github.io/pointtorch/changelog
Keywords: point cloud,deep learning,pytorch
Classifier: Development Status :: 4 - Beta
Classifier: Intended Audience :: Science/Research
Classifier: License :: OSI Approved :: MIT License
Classifier: Programming Language :: Python
Classifier: Programming Language :: Python :: 3 :: Only
Classifier: Programming Language :: Python :: 3.9
Classifier: Programming Language :: Python :: 3.10
Classifier: Programming Language :: Python :: 3.11
Classifier: Programming Language :: Python :: 3.12
Classifier: Programming Language :: Python :: 3.13
Classifier: Topic :: Scientific/Engineering :: Artificial Intelligence
Requires-Python: >=3.9
License-File: LICENSE
Requires-Dist: h5py<4.0.0,>=3.5.0
Requires-Dist: laspy<3.0.0,>=2.0.0
Requires-Dist: laszip<3.0.0,>=0.2.0
Requires-Dist: lazrs<1.0.0,>=0.5.0
Requires-Dist: numpy<3.0.0,>=1.21.0
Requires-Dist: pandas<3.0.0,>=2.0.0
Requires-Dist: pyproj<4.0.0,>=3.4.0
Requires-Dist: scikit-learn<2.0.0,>=1.2.0
Requires-Dist: tables<4.0.0,>=3.8.0
Requires-Dist: tqdm<5.0.0,>=4.60.0
Provides-Extra: dev
Requires-Dist: black; extra == "dev"
Requires-Dist: hypothesis; extra == "dev"
Requires-Dist: mypy; extra == "dev"
Requires-Dist: pandas-stubs; extra == "dev"
Requires-Dist: pre-commit; extra == "dev"
Requires-Dist: pylint; extra == "dev"
Requires-Dist: pytest; extra == "dev"
Requires-Dist: pytest-cov; extra == "dev"
Requires-Dist: pytest-httpserver; extra == "dev"
Requires-Dist: types-tqdm; extra == "dev"
Provides-Extra: docs
Requires-Dist: sphinx; extra == "docs"
Requires-Dist: sphinx-copybutton; extra == "docs"
Requires-Dist: sphinx-design; extra == "docs"
Requires-Dist: sphinx-docsearch; extra == "docs"
Requires-Dist: sphinxawesome-theme; extra == "docs"
Requires-Dist: sphinx-sitemap; extra == "docs"
Requires-Dist: sphinxcontrib-jsmath; extra == "docs"
Requires-Dist: sphinxcontrib-katex; extra == "docs"
Requires-Dist: sphinxcontrib-napoleon; extra == "docs"
Requires-Dist: sphinx_mdinclude; extra == "docs"
